Metadata-Version: 2.1
Name: ep-launch
Version: 3.5.3
Summary: Graphical Interface and Workflow Manager for EnergyPlus
Home-page: https://github.com/NREL/EP-Launch
Author: Jason Glazer and Edwin Lee for the United States Department of Energy
License: ModifiedBSD
Platform: UNKNOWN
